[{"x": 98, "y": 81, "label_id": 3}, {"x": 138, "y": 122, "label_id": 3}, {"x": 136, "y": 132, "label_id": 3}, {"x": 72, "y": 80, "label_id": 3}, {"x": 127, "y": 37, "label_id": 3}, {"x": 70, "y": 184, "label_id": 3}, {"x": 77, "y": 200, "label_id": 3}, {"x": 146, "y": 163, "label_id": 3}, {"x": 16, "y": 113, "label_id": 3}, {"x": 126, "y": 7, "label_id": 3}, {"x": 69, "y": 135, "label_id": 3}, {"x": 171, "y": 173, "label_id": 3}, {"x": 218, "y": 7, "label_id": 3}, {"x": 68, "y": 117, "label_id": 3}]