[{"x": 60, "y": 30, "label_id": 1}, {"x": 79, "y": 19, "label_id": 1}, {"x": 68, "y": 9, "label_id": 1}, {"x": 97, "y": 32, "label_id": 1}, {"x": 70, "y": 69, "label_id": 1}, {"x": 42, "y": 58, "label_id": 1}, {"x": 23, "y": 63, "label_id": 1}, {"x": 36, "y": 69, "label_id": 1}, {"x": 35, "y": 95, "label_id": 1}, {"x": 26, "y": 105, "label_id": 1}, {"x": 37, "y": 111, "label_id": 1}, {"x": 52, "y": 110, "label_id": 1}, {"x": 60, "y": 115, "label_id": 1}, {"x": 76, "y": 106, "label_id": 1}, {"x": 77, "y": 86, "label_id": 1}, {"x": 178, "y": 42, "label_id": 1}, {"x": 158, "y": 46, "label_id": 1}, {"x": 142, "y": 42, "label_id": 1}, {"x": 218, "y": 57, "label_id": 1}, {"x": 201, "y": 57, "label_id": 1}, {"x": 187, "y": 64, "label_id": 1}, {"x": 252, "y": 12, "label_id": 1}, {"x": 136, "y": 148, "label_id": 1}, {"x": 121, "y": 136, "label_id": 1}, {"x": 105, "y": 124, "label_id": 1}, {"x": 98, "y": 133, "label_id": 1}, {"x": 84, "y": 146, "label_id": 1}, {"x": 73, "y": 135, "label_id": 1}, {"x": 56, "y": 128, "label_id": 1}, {"x": 65, "y": 148, "label_id": 1}, {"x": 48, "y": 138, "label_id": 1}, {"x": 28, "y": 142, "label_id": 1}, {"x": 39, "y": 162, "label_id": 1}, {"x": 40, "y": 193, "label_id": 1}, {"x": 81, "y": 160, "label_id": 1}, {"x": 65, "y": 160, "label_id": 1}, {"x": 100, "y": 166, "label_id": 1}, {"x": 147, "y": 175, "label_id": 1}, {"x": 158, "y": 162, "label_id": 1}, {"x": 117, "y": 165, "label_id": 1}, {"x": 175, "y": 189, "label_id": 1}, {"x": 165, "y": 172, "label_id": 1}, {"x": 185, "y": 205, "label_id": 1}, {"x": 172, "y": 208, "label_id": 1}, {"x": 157, "y": 208, "label_id": 1}, {"x": 165, "y": 233, "label_id": 1}, {"x": 143, "y": 223, "label_id": 1}, {"x": 100, "y": 198, "label_id": 1}, {"x": 84, "y": 205, "label_id": 1}, {"x": 61, "y": 194, "label_id": 1}, {"x": 47, "y": 215, "label_id": 1}, {"x": 238, "y": 239, "label_id": 1}, {"x": 247, "y": 228, "label_id": 1}, {"x": 179, "y": 229, "label_id": 1}, {"x": 44, "y": 37, "label_id": 2}, {"x": 49, "y": 51, "label_id": 2}, {"x": 61, "y": 50, "label_id": 2}, {"x": 87, "y": 28, "label_id": 2}, {"x": 53, "y": 79, "label_id": 2}, {"x": 58, "y": 96, "label_id": 2}, {"x": 57, "y": 175, "label_id": 2}, {"x": 97, "y": 152, "label_id": 2}, {"x": 114, "y": 148, "label_id": 2}, {"x": 137, "y": 134, "label_id": 2}, {"x": 163, "y": 149, "label_id": 2}, {"x": 94, "y": 109, "label_id": 2}, {"x": 79, "y": 177, "label_id": 2}, {"x": 78, "y": 205, "label_id": 2}, {"x": 74, "y": 221, "label_id": 2}, {"x": 92, "y": 215, "label_id": 2}, {"x": 111, "y": 206, "label_id": 2}, {"x": 101, "y": 227, "label_id": 2}, {"x": 124, "y": 199, "label_id": 2}, {"x": 143, "y": 191, "label_id": 2}, {"x": 156, "y": 191, "label_id": 2}, {"x": 198, "y": 230, "label_id": 2}, {"x": 131, "y": 231, "label_id": 2}, {"x": 224, "y": 72, "label_id": 2}, {"x": 212, "y": 80, "label_id": 2}, {"x": 195, "y": 80, "label_id": 2}, {"x": 194, "y": 45, "label_id": 2}, {"x": 153, "y": 34, "label_id": 2}, {"x": 144, "y": 25, "label_id": 2}, {"x": 39, "y": 178, "label_id": 2}, {"x": 249, "y": 239, "label_id": 1}]