[{"x": 62, "y": 48, "label_id": 1}, {"x": 27, "y": 81, "label_id": 1}, {"x": 122, "y": 123, "label_id": 1}, {"x": 180, "y": 123, "label_id": 1}, {"x": 194, "y": 123, "label_id": 1}, {"x": 123, "y": 157, "label_id": 1}, {"x": 145, "y": 158, "label_id": 1}, {"x": 135, "y": 160, "label_id": 1}, {"x": 160, "y": 172, "label_id": 1}, {"x": 74, "y": 188, "label_id": 1}, {"x": 69, "y": 10, "label_id": 2}, {"x": 158, "y": 16, "label_id": 2}, {"x": 165, "y": 24, "label_id": 2}, {"x": 31, "y": 26, "label_id": 2}, {"x": 19, "y": 27, "label_id": 2}, {"x": 223, "y": 33, "label_id": 2}, {"x": 111, "y": 38, "label_id": 2}, {"x": 44, "y": 48, "label_id": 2}, {"x": 120, "y": 52, "label_id": 2}, {"x": 9, "y": 57, "label_id": 2}, {"x": 75, "y": 59, "label_id": 2}, {"x": 19, "y": 64, "label_id": 2}, {"x": 69, "y": 71, "label_id": 2}, {"x": 79, "y": 73, "label_id": 2}, {"x": 53, "y": 79, "label_id": 2}, {"x": 148, "y": 84, "label_id": 2}, {"x": 3, "y": 85, "label_id": 2}, {"x": 118, "y": 88, "label_id": 2}, {"x": 161, "y": 94, "label_id": 2}, {"x": 42, "y": 95, "label_id": 2}, {"x": 12, "y": 96, "label_id": 2}, {"x": 128, "y": 99, "label_id": 2}, {"x": 28, "y": 100, "label_id": 2}, {"x": 149, "y": 102, "label_id": 2}, {"x": 161, "y": 105, "label_id": 2}, {"x": 143, "y": 110, "label_id": 2}, {"x": 107, "y": 114, "label_id": 2}, {"x": 58, "y": 119, "label_id": 2}, {"x": 165, "y": 119, "label_id": 2}, {"x": 38, "y": 124, "label_id": 2}, {"x": 66, "y": 132, "label_id": 2}, {"x": 171, "y": 137, "label_id": 2}, {"x": 54, "y": 137, "label_id": 2}, {"x": 117, "y": 137, "label_id": 2}, {"x": 186, "y": 143, "label_id": 2}, {"x": 178, "y": 153, "label_id": 2}, {"x": 222, "y": 157, "label_id": 2}, {"x": 135, "y": 159, "label_id": 2}, {"x": 165, "y": 159, "label_id": 2}, {"x": 206, "y": 164, "label_id": 2}, {"x": 193, "y": 165, "label_id": 2}, {"x": 133, "y": 171, "label_id": 2}, {"x": 185, "y": 176, "label_id": 2}, {"x": 46, "y": 182, "label_id": 2}, {"x": 83, "y": 187, "label_id": 2}, {"x": 7, "y": 192, "label_id": 2}, {"x": 57, "y": 194, "label_id": 2}, {"x": 34, "y": 197, "label_id": 2}, {"x": 61, "y": 208, "label_id": 2}, {"x": 122, "y": 218, "label_id": 2}, {"x": 186, "y": 240, "label_id": 1}, {"x": 123, "y": 107, "label_id": 2}, {"x": 250, "y": 154, "label_id": 2}, {"x": 230, "y": 135, "label_id": 2}]