[{"x": 169, "y": 139, "label_id": 1}, {"x": 193, "y": 160, "label_id": 1}, {"x": 184, "y": 200, "label_id": 1}, {"x": 5, "y": 215, "label_id": 1}, {"x": 166, "y": 237, "label_id": 1}, {"x": 251, "y": 2, "label_id": 2}, {"x": 10, "y": 2, "label_id": 2}, {"x": 242, "y": 2, "label_id": 2}, {"x": 192, "y": 3, "label_id": 2}, {"x": 184, "y": 6, "label_id": 2}, {"x": 210, "y": 6, "label_id": 2}, {"x": 2, "y": 7, "label_id": 2}, {"x": 22, "y": 8, "label_id": 2}, {"x": 115, "y": 9, "label_id": 2}, {"x": 124, "y": 11, "label_id": 2}, {"x": 227, "y": 11, "label_id": 2}, {"x": 12, "y": 11, "label_id": 2}, {"x": 234, "y": 12, "label_id": 2}, {"x": 245, "y": 13, "label_id": 2}, {"x": 185, "y": 17, "label_id": 2}, {"x": 250, "y": 16, "label_id": 2}, {"x": 100, "y": 18, "label_id": 2}, {"x": 4, "y": 20, "label_id": 2}, {"x": 207, "y": 22, "label_id": 2}, {"x": 128, "y": 24, "label_id": 2}, {"x": 111, "y": 27, "label_id": 2}, {"x": 196, "y": 28, "label_id": 2}, {"x": 15, "y": 28, "label_id": 2}, {"x": 91, "y": 29, "label_id": 2}, {"x": 76, "y": 31, "label_id": 2}, {"x": 132, "y": 34, "label_id": 2}, {"x": 207, "y": 35, "label_id": 2}, {"x": 218, "y": 35, "label_id": 2}, {"x": 186, "y": 36, "label_id": 2}, {"x": 116, "y": 37, "label_id": 2}, {"x": 198, "y": 38, "label_id": 2}, {"x": 187, "y": 44, "label_id": 2}, {"x": 67, "y": 44, "label_id": 2}, {"x": 105, "y": 46, "label_id": 2}, {"x": 214, "y": 46, "label_id": 2}, {"x": 194, "y": 51, "label_id": 2}, {"x": 121, "y": 50, "label_id": 2}, {"x": 124, "y": 50, "label_id": 2}, {"x": 3, "y": 54, "label_id": 2}, {"x": 66, "y": 54, "label_id": 2}, {"x": 88, "y": 54, "label_id": 2}, {"x": 56, "y": 56, "label_id": 2}, {"x": 200, "y": 57, "label_id": 2}, {"x": 74, "y": 59, "label_id": 2}, {"x": 179, "y": 60, "label_id": 2}, {"x": 215, "y": 60, "label_id": 2}, {"x": 50, "y": 62, "label_id": 2}, {"x": 114, "y": 62, "label_id": 2}, {"x": 145, "y": 64, "label_id": 2}, {"x": 2, "y": 64, "label_id": 2}, {"x": 67, "y": 64, "label_id": 2}, {"x": 203, "y": 68, "label_id": 2}, {"x": 119, "y": 68, "label_id": 2}, {"x": 54, "y": 68, "label_id": 2}, {"x": 102, "y": 69, "label_id": 2}, {"x": 85, "y": 69, "label_id": 2}, {"x": 219, "y": 72, "label_id": 2}, {"x": 75, "y": 73, "label_id": 2}, {"x": 49, "y": 77, "label_id": 2}, {"x": 97, "y": 78, "label_id": 2}, {"x": 251, "y": 77, "label_id": 2}, {"x": 40, "y": 77, "label_id": 2}, {"x": 108, "y": 78, "label_id": 2}, {"x": 212, "y": 79, "label_id": 2}, {"x": 242, "y": 81, "label_id": 2}, {"x": 34, "y": 85, "label_id": 2}, {"x": 45, "y": 87, "label_id": 2}, {"x": 233, "y": 87, "label_id": 2}, {"x": 65, "y": 87, "label_id": 2}, {"x": 103, "y": 89, "label_id": 2}, {"x": 27, "y": 92, "label_id": 2}, {"x": 246, "y": 92, "label_id": 2}, {"x": 239, "y": 98, "label_id": 2}, {"x": 35, "y": 102, "label_id": 2}, {"x": 247, "y": 102, "label_id": 2}, {"x": 96, "y": 100, "label_id": 2}, {"x": 79, "y": 103, "label_id": 2}, {"x": 19, "y": 106, "label_id": 2}, {"x": 89, "y": 109, "label_id": 2}, {"x": 28, "y": 112, "label_id": 2}, {"x": 162, "y": 118, "label_id": 2}, {"x": 86, "y": 119, "label_id": 2}, {"x": 145, "y": 125, "label_id": 2}, {"x": 31, "y": 126, "label_id": 2}, {"x": 73, "y": 126, "label_id": 2}, {"x": 169, "y": 128, "label_id": 2}, {"x": 222, "y": 130, "label_id": 2}, {"x": 19, "y": 132, "label_id": 2}, {"x": 160, "y": 134, "label_id": 2}, {"x": 37, "y": 135, "label_id": 2}, {"x": 50, "y": 135, "label_id": 2}, {"x": 64, "y": 138, "label_id": 2}, {"x": 193, "y": 140, "label_id": 2}, {"x": 136, "y": 141, "label_id": 2}, {"x": 19, "y": 142, "label_id": 2}, {"x": 29, "y": 143, "label_id": 2}, {"x": 69, "y": 147, "label_id": 2}, {"x": 178, "y": 148, "label_id": 2}, {"x": 156, "y": 148, "label_id": 2}, {"x": 122, "y": 150, "label_id": 2}, {"x": 167, "y": 151, "label_id": 2}, {"x": 145, "y": 153, "label_id": 2}, {"x": 63, "y": 153, "label_id": 2}, {"x": 22, "y": 156, "label_id": 2}, {"x": 46, "y": 158, "label_id": 2}, {"x": 57, "y": 160, "label_id": 2}, {"x": 29, "y": 162, "label_id": 2}, {"x": 167, "y": 162, "label_id": 2}, {"x": 133, "y": 163, "label_id": 2}, {"x": 151, "y": 164, "label_id": 2}, {"x": 108, "y": 167, "label_id": 2}, {"x": 34, "y": 170, "label_id": 2}, {"x": 192, "y": 172, "label_id": 2}, {"x": 47, "y": 172, "label_id": 2}, {"x": 60, "y": 172, "label_id": 2}, {"x": 163, "y": 174, "label_id": 2}, {"x": 120, "y": 174, "label_id": 2}, {"x": 178, "y": 175, "label_id": 2}, {"x": 40, "y": 179, "label_id": 2}, {"x": 131, "y": 180, "label_id": 2}, {"x": 155, "y": 185, "label_id": 2}, {"x": 172, "y": 187, "label_id": 2}, {"x": 117, "y": 188, "label_id": 2}, {"x": 89, "y": 189, "label_id": 2}, {"x": 141, "y": 189, "label_id": 2}, {"x": 170, "y": 198, "label_id": 2}, {"x": 76, "y": 199, "label_id": 2}, {"x": 128, "y": 200, "label_id": 2}, {"x": 111, "y": 201, "label_id": 2}, {"x": 153, "y": 204, "label_id": 2}, {"x": 89, "y": 208, "label_id": 2}, {"x": 172, "y": 209, "label_id": 2}, {"x": 77, "y": 211, "label_id": 2}, {"x": 65, "y": 211, "label_id": 2}, {"x": 248, "y": 216, "label_id": 2}, {"x": 80, "y": 217, "label_id": 2}, {"x": 182, "y": 220, "label_id": 2}, {"x": 127, "y": 221, "label_id": 2}, {"x": 248, "y": 223, "label_id": 2}, {"x": 94, "y": 226, "label_id": 2}, {"x": 169, "y": 226, "label_id": 2}, {"x": 64, "y": 226, "label_id": 2}, {"x": 142, "y": 227, "label_id": 2}, {"x": 39, "y": 229, "label_id": 2}, {"x": 53, "y": 231, "label_id": 2}, {"x": 85, "y": 231, "label_id": 2}, {"x": 70, "y": 236, "label_id": 2}, {"x": 151, "y": 241, "label_id": 2}, {"x": 80, "y": 242, "label_id": 2}, {"x": 58, "y": 244, "label_id": 2}, {"x": 140, "y": 246, "label_id": 2}, {"x": 225, "y": 248, "label_id": 2}, {"x": 68, "y": 249, "label_id": 2}, {"x": 63, "y": 103, "label_id": 2}, {"x": 74, "y": 116, "label_id": 2}, {"x": 40, "y": 119, "label_id": 2}, {"x": 45, "y": 104, "label_id": 2}, {"x": 92, "y": 19, "label_id": 2}, {"x": 184, "y": 186, "label_id": 2}, {"x": 209, "y": 175, "label_id": 2}, {"x": 149, "y": 141, "label_id": 2}, {"x": 221, "y": 8, "label_id": 2}, {"x": 30, "y": 35, "label_id": 2}]