[{"x": 153, "y": 48, "label_id": 3}, {"x": 164, "y": 36, "label_id": 3}, {"x": 184, "y": 17, "label_id": 3}, {"x": 142, "y": 26, "label_id": 3}, {"x": 145, "y": 7, "label_id": 3}, {"x": 232, "y": 93, "label_id": 3}, {"x": 177, "y": 77, "label_id": 3}, {"x": 177, "y": 64, "label_id": 3}, {"x": 199, "y": 124, "label_id": 3}, {"x": 177, "y": 70, "label_id": 3}, {"x": 178, "y": 31, "label_id": 3}, {"x": 197, "y": 119, "label_id": 3}, {"x": 179, "y": 89, "label_id": 3}, {"x": 244, "y": 42, "label_id": 3}, {"x": 197, "y": 36, "label_id": 3}, {"x": 236, "y": 115, "label_id": 3}, {"x": 248, "y": 145, "label_id": 3}, {"x": 228, "y": 144, "label_id": 3}, {"x": 219, "y": 127, "label_id": 3}, {"x": 191, "y": 64, "label_id": 3}, {"x": 246, "y": 67, "label_id": 3}, {"x": 218, "y": 61, "label_id": 3}, {"x": 246, "y": 171, "label_id": 3}, {"x": 248, "y": 204, "label_id": 3}, {"x": 175, "y": 14, "label_id": 3}, {"x": 210, "y": 90, "label_id": 3}, {"x": 184, "y": 56, "label_id": 3}, {"x": 230, "y": 75, "label_id": 3}, {"x": 239, "y": 185, "label_id": 3}, {"x": 222, "y": 102, "label_id": 3}, {"x": 226, "y": 88, "label_id": 3}, {"x": 202, "y": 66, "label_id": 3}, {"x": 250, "y": 194, "label_id": 3}]