[{"x": 106, "y": 0, "label_id": 1}, {"x": 240, "y": 3, "label_id": 1}, {"x": 108, "y": 16, "label_id": 1}, {"x": 88, "y": 23, "label_id": 1}, {"x": 2, "y": 26, "label_id": 1}, {"x": 58, "y": 37, "label_id": 1}, {"x": 161, "y": 38, "label_id": 1}, {"x": 90, "y": 40, "label_id": 1}, {"x": 104, "y": 44, "label_id": 1}, {"x": 144, "y": 55, "label_id": 1}, {"x": 236, "y": 61, "label_id": 1}, {"x": 163, "y": 64, "label_id": 1}, {"x": 10, "y": 65, "label_id": 1}, {"x": 177, "y": 67, "label_id": 1}, {"x": 111, "y": 77, "label_id": 1}, {"x": 170, "y": 85, "label_id": 1}, {"x": 245, "y": 101, "label_id": 1}, {"x": 95, "y": 103, "label_id": 1}, {"x": 32, "y": 106, "label_id": 1}, {"x": 128, "y": 106, "label_id": 1}, {"x": 76, "y": 106, "label_id": 1}, {"x": 180, "y": 116, "label_id": 1}, {"x": 224, "y": 128, "label_id": 1}, {"x": 164, "y": 129, "label_id": 1}, {"x": 244, "y": 135, "label_id": 1}, {"x": 158, "y": 177, "label_id": 1}, {"x": 68, "y": 181, "label_id": 1}, {"x": 176, "y": 183, "label_id": 1}, {"x": 17, "y": 184, "label_id": 1}, {"x": 40, "y": 203, "label_id": 1}, {"x": 36, "y": 213, "label_id": 1}, {"x": 91, "y": 217, "label_id": 1}, {"x": 85, "y": 225, "label_id": 1}, {"x": 13, "y": 2, "label_id": 2}, {"x": 222, "y": 3, "label_id": 2}, {"x": 53, "y": 4, "label_id": 2}, {"x": 151, "y": 3, "label_id": 2}, {"x": 74, "y": 5, "label_id": 2}, {"x": 6, "y": 10, "label_id": 2}, {"x": 27, "y": 10, "label_id": 2}, {"x": 212, "y": 16, "label_id": 2}, {"x": 15, "y": 31, "label_id": 2}, {"x": 201, "y": 32, "label_id": 2}, {"x": 43, "y": 36, "label_id": 2}, {"x": 227, "y": 39, "label_id": 2}, {"x": 28, "y": 39, "label_id": 2}, {"x": 195, "y": 43, "label_id": 2}, {"x": 210, "y": 48, "label_id": 2}, {"x": 16, "y": 48, "label_id": 2}, {"x": 51, "y": 48, "label_id": 2}, {"x": 2, "y": 49, "label_id": 2}, {"x": 40, "y": 50, "label_id": 2}, {"x": 123, "y": 52, "label_id": 2}, {"x": 40, "y": 66, "label_id": 2}, {"x": 138, "y": 67, "label_id": 2}, {"x": 76, "y": 73, "label_id": 2}, {"x": 191, "y": 77, "label_id": 2}, {"x": 38, "y": 78, "label_id": 2}, {"x": 125, "y": 79, "label_id": 2}, {"x": 24, "y": 80, "label_id": 2}, {"x": 147, "y": 83, "label_id": 2}, {"x": 69, "y": 87, "label_id": 2}, {"x": 33, "y": 87, "label_id": 2}, {"x": 124, "y": 88, "label_id": 2}, {"x": 222, "y": 89, "label_id": 2}, {"x": 232, "y": 94, "label_id": 2}, {"x": 156, "y": 95, "label_id": 2}, {"x": 131, "y": 97, "label_id": 2}, {"x": 6, "y": 100, "label_id": 2}, {"x": 56, "y": 102, "label_id": 2}, {"x": 66, "y": 101, "label_id": 2}, {"x": 208, "y": 103, "label_id": 2}, {"x": 103, "y": 112, "label_id": 2}, {"x": 203, "y": 115, "label_id": 2}, {"x": 20, "y": 114, "label_id": 2}, {"x": 6, "y": 116, "label_id": 2}, {"x": 96, "y": 117, "label_id": 2}, {"x": 58, "y": 122, "label_id": 2}, {"x": 196, "y": 123, "label_id": 2}, {"x": 148, "y": 130, "label_id": 2}, {"x": 12, "y": 132, "label_id": 2}, {"x": 91, "y": 133, "label_id": 2}, {"x": 80, "y": 140, "label_id": 2}, {"x": 194, "y": 140, "label_id": 2}, {"x": 32, "y": 141, "label_id": 2}, {"x": 3, "y": 142, "label_id": 2}, {"x": 112, "y": 141, "label_id": 2}, {"x": 150, "y": 143, "label_id": 2}, {"x": 131, "y": 144, "label_id": 2}, {"x": 179, "y": 148, "label_id": 2}, {"x": 233, "y": 148, "label_id": 2}, {"x": 215, "y": 149, "label_id": 2}, {"x": 6, "y": 153, "label_id": 2}, {"x": 26, "y": 154, "label_id": 2}, {"x": 78, "y": 154, "label_id": 2}, {"x": 133, "y": 155, "label_id": 2}, {"x": 66, "y": 160, "label_id": 2}, {"x": 185, "y": 161, "label_id": 2}, {"x": 121, "y": 163, "label_id": 2}, {"x": 4, "y": 167, "label_id": 2}, {"x": 203, "y": 170, "label_id": 2}, {"x": 219, "y": 173, "label_id": 2}, {"x": 193, "y": 174, "label_id": 2}, {"x": 92, "y": 184, "label_id": 2}, {"x": 122, "y": 184, "label_id": 2}, {"x": 55, "y": 186, "label_id": 2}, {"x": 73, "y": 189, "label_id": 2}, {"x": 195, "y": 189, "label_id": 2}, {"x": 213, "y": 189, "label_id": 2}, {"x": 29, "y": 191, "label_id": 2}, {"x": 3, "y": 194, "label_id": 2}, {"x": 61, "y": 197, "label_id": 2}, {"x": 115, "y": 197, "label_id": 2}, {"x": 85, "y": 197, "label_id": 2}, {"x": 128, "y": 197, "label_id": 2}, {"x": 167, "y": 198, "label_id": 2}, {"x": 180, "y": 201, "label_id": 2}, {"x": 201, "y": 203, "label_id": 2}, {"x": 22, "y": 205, "label_id": 2}, {"x": 233, "y": 207, "label_id": 2}, {"x": 146, "y": 208, "label_id": 2}, {"x": 18, "y": 216, "label_id": 2}, {"x": 74, "y": 218, "label_id": 2}, {"x": 122, "y": 218, "label_id": 2}, {"x": 3, "y": 219, "label_id": 2}, {"x": 235, "y": 223, "label_id": 2}, {"x": 100, "y": 224, "label_id": 2}, {"x": 251, "y": 224, "label_id": 2}, {"x": 195, "y": 229, "label_id": 2}, {"x": 64, "y": 231, "label_id": 2}, {"x": 251, "y": 235, "label_id": 2}, {"x": 72, "y": 236, "label_id": 2}, {"x": 94, "y": 236, "label_id": 2}, {"x": 213, "y": 240, "label_id": 2}, {"x": 3, "y": 240, "label_id": 2}, {"x": 87, "y": 245, "label_id": 2}, {"x": 12, "y": 246, "label_id": 2}, {"x": 182, "y": 247, "label_id": 2}, {"x": 135, "y": 248, "label_id": 2}, {"x": 53, "y": 249, "label_id": 2}, {"x": 71, "y": 58, "label_id": 2}, {"x": 66, "y": 67, "label_id": 2}, {"x": 230, "y": 158, "label_id": 2}, {"x": 177, "y": 234, "label_id": 2}, {"x": 194, "y": 254, "label_id": 2}, {"x": 127, "y": 209, "label_id": 2}, {"x": 87, "y": 209, "label_id": 2}, {"x": 13, "y": 84, "label_id": 1}, {"x": 100, "y": 199, "label_id": 2}, {"x": 66, "y": 122, "label_id": 2}, {"x": 52, "y": 141, "label_id": 1}, {"x": 51, "y": 123, "label_id": 1}, {"x": 104, "y": 172, "label_id": 3}, {"x": 61, "y": 83, "label_id": 3}]