[{"x": 234, "y": 25, "label_id": 1}, {"x": 211, "y": 26, "label_id": 1}, {"x": 179, "y": 40, "label_id": 1}, {"x": 89, "y": 58, "label_id": 1}, {"x": 217, "y": 69, "label_id": 1}, {"x": 2, "y": 104, "label_id": 1}, {"x": 20, "y": 128, "label_id": 1}, {"x": 170, "y": 132, "label_id": 1}, {"x": 194, "y": 143, "label_id": 1}, {"x": 208, "y": 149, "label_id": 1}, {"x": 188, "y": 157, "label_id": 1}, {"x": 242, "y": 160, "label_id": 1}, {"x": 53, "y": 164, "label_id": 1}, {"x": 3, "y": 175, "label_id": 1}, {"x": 215, "y": 192, "label_id": 1}, {"x": 228, "y": 199, "label_id": 1}, {"x": 175, "y": 221, "label_id": 1}, {"x": 227, "y": 221, "label_id": 1}, {"x": 3, "y": 244, "label_id": 1}, {"x": 64, "y": 247, "label_id": 1}, {"x": 196, "y": 2, "label_id": 2}, {"x": 82, "y": 6, "label_id": 2}, {"x": 107, "y": 8, "label_id": 2}, {"x": 243, "y": 11, "label_id": 2}, {"x": 163, "y": 12, "label_id": 2}, {"x": 16, "y": 13, "label_id": 2}, {"x": 184, "y": 15, "label_id": 2}, {"x": 138, "y": 17, "label_id": 2}, {"x": 62, "y": 23, "label_id": 2}, {"x": 103, "y": 29, "label_id": 2}, {"x": 244, "y": 32, "label_id": 2}, {"x": 82, "y": 35, "label_id": 2}, {"x": 142, "y": 41, "label_id": 2}, {"x": 227, "y": 42, "label_id": 2}, {"x": 157, "y": 42, "label_id": 2}, {"x": 114, "y": 52, "label_id": 2}, {"x": 168, "y": 56, "label_id": 2}, {"x": 241, "y": 57, "label_id": 2}, {"x": 71, "y": 59, "label_id": 2}, {"x": 58, "y": 65, "label_id": 2}, {"x": 156, "y": 69, "label_id": 2}, {"x": 3, "y": 70, "label_id": 2}, {"x": 130, "y": 74, "label_id": 2}, {"x": 233, "y": 75, "label_id": 2}, {"x": 41, "y": 77, "label_id": 2}, {"x": 16, "y": 81, "label_id": 2}, {"x": 86, "y": 85, "label_id": 2}, {"x": 3, "y": 88, "label_id": 2}, {"x": 161, "y": 89, "label_id": 2}, {"x": 128, "y": 94, "label_id": 2}, {"x": 71, "y": 99, "label_id": 2}, {"x": 225, "y": 99, "label_id": 2}, {"x": 15, "y": 101, "label_id": 2}, {"x": 104, "y": 109, "label_id": 2}, {"x": 40, "y": 110, "label_id": 2}, {"x": 56, "y": 112, "label_id": 2}, {"x": 75, "y": 114, "label_id": 2}, {"x": 132, "y": 115, "label_id": 2}, {"x": 224, "y": 120, "label_id": 2}, {"x": 91, "y": 121, "label_id": 2}, {"x": 49, "y": 122, "label_id": 2}, {"x": 246, "y": 123, "label_id": 2}, {"x": 115, "y": 127, "label_id": 2}, {"x": 101, "y": 131, "label_id": 2}, {"x": 78, "y": 133, "label_id": 2}, {"x": 240, "y": 139, "label_id": 2}, {"x": 124, "y": 144, "label_id": 2}, {"x": 66, "y": 147, "label_id": 2}, {"x": 31, "y": 150, "label_id": 2}, {"x": 103, "y": 151, "label_id": 2}, {"x": 157, "y": 152, "label_id": 2}, {"x": 214, "y": 161, "label_id": 2}, {"x": 120, "y": 162, "label_id": 2}, {"x": 25, "y": 169, "label_id": 2}, {"x": 163, "y": 169, "label_id": 2}, {"x": 83, "y": 170, "label_id": 2}, {"x": 113, "y": 174, "label_id": 2}, {"x": 143, "y": 174, "label_id": 2}, {"x": 64, "y": 178, "label_id": 2}, {"x": 215, "y": 180, "label_id": 2}, {"x": 237, "y": 181, "label_id": 2}, {"x": 100, "y": 181, "label_id": 2}, {"x": 122, "y": 182, "label_id": 2}, {"x": 158, "y": 188, "label_id": 2}, {"x": 88, "y": 191, "label_id": 2}, {"x": 47, "y": 195, "label_id": 2}, {"x": 188, "y": 196, "label_id": 2}, {"x": 114, "y": 198, "label_id": 2}, {"x": 131, "y": 202, "label_id": 2}, {"x": 201, "y": 206, "label_id": 2}, {"x": 98, "y": 208, "label_id": 2}, {"x": 81, "y": 211, "label_id": 2}, {"x": 4, "y": 212, "label_id": 2}, {"x": 33, "y": 212, "label_id": 2}, {"x": 121, "y": 213, "label_id": 2}, {"x": 53, "y": 215, "label_id": 2}, {"x": 151, "y": 218, "label_id": 2}, {"x": 73, "y": 219, "label_id": 2}, {"x": 199, "y": 218, "label_id": 2}, {"x": 90, "y": 222, "label_id": 2}, {"x": 17, "y": 224, "label_id": 2}, {"x": 84, "y": 233, "label_id": 2}, {"x": 218, "y": 233, "label_id": 2}, {"x": 246, "y": 234, "label_id": 2}, {"x": 30, "y": 237, "label_id": 2}, {"x": 160, "y": 236, "label_id": 2}, {"x": 120, "y": 251, "label_id": 2}, {"x": 207, "y": 110, "label_id": 2}, {"x": 206, "y": 122, "label_id": 2}, {"x": 218, "y": 115, "label_id": 2}, {"x": 201, "y": 68, "label_id": 3}, {"x": 217, "y": 214, "label_id": 1}, {"x": 133, "y": 240, "label_id": 1}, {"x": 140, "y": 254, "label_id": 1}, {"x": 140, "y": 27, "label_id": 1}, {"x": 198, "y": 239, "label_id": 3}, {"x": 41, "y": 221, "label_id": 2}, {"x": 112, "y": 241, "label_id": 2}, {"x": 84, "y": 73, "label_id": 2}, {"x": 214, "y": 60, "label_id": 2}, {"x": 230, "y": 58, "label_id": 2}, {"x": 239, "y": 91, "label_id": 2}, {"x": 111, "y": 220, "label_id": 2}, {"x": 122, "y": 229, "label_id": 2}, {"x": 9, "y": 2, "label_id": 2}, {"x": 212, "y": 248, "label_id": 2}, {"x": 97, "y": 249, "label_id": 2}, {"x": 46, "y": 56, "label_id": 2}, {"x": 176, "y": 113, "label_id": 2}, {"x": 17, "y": 29, "label_id": 1}, {"x": 173, "y": 154, "label_id": 1}, {"x": 5, "y": 159, "label_id": 1}, {"x": 223, "y": 65, "label_id": 1}, {"x": 250, "y": 252, "label_id": 1}]